MANIFEST.in
README.rst
setup.cfg
setup.py
auspost/__init__.py
auspost/common.py
auspost/delivery_choice.py
auspost_apis.egg-info/PKG-INFO
auspost_apis.egg-info/SOURCES.txt
auspost_apis.egg-info/dependency_links.txt
auspost_apis.egg-info/requires.txt
auspost_apis.egg-info/top_level.txt