Metadata-Version: 1.1
Name: auspost-apis
Version: 0.1
Summary: A Python wrapper around Australia Post's APIs
Home-page: https://github.com/elbaschid/auspost-apis
Author: Sebastian Vetter
Author-email: sebastian.vetter@tangentsnowball.com.au
License: BSD
Keywords: wrapper,logistics,delivery,post,Australia
Platform: linux
Classifier: Environment :: Web Environment
Classifier: Intended Audience :: Developers
Classifier: License :: OSI Approved :: BSD License
Classifier: Operating System :: Unix
Classifier: Programming Language :: Python
